{"chart1":[{"Net Sales":"16497161","Gross Sales":"19754076","Total Orders":"2368.0","State":"Maharashtra"},{"Net Sales":"14883919","Gross Sales":"17684105","Total Orders":"2117.0","State":"Uttar Pradesh"},{"Net Sales":"14935780","Gross Sales":"17679156","Total Orders":"1980.0","State":"Andhra Pradesh"},{"Net Sales":"13331257","Gross Sales":"16180442","Total Orders":"1753.0","State":"Haryana"},{"Net Sales":"11302392","Gross Sales":"13462071","Total Orders":"1533.0","State":"West Bengal"},{"Net Sales":"9682876.0","Gross Sales":"11642640","Total Orders":"1389.0","State":"Karnataka"},{"Net Sales":"9688333.0","Gross Sales":"11411836","Total Orders":"1420.0","State":"Gujarat"},{"Net Sales":"8661532.0","Gross Sales":"10364676","Total Orders":"1079.0","State":"Madhya Pradesh"},{"Net Sales":"8613087.0","Gross Sales":"10331433","Total Orders":"1164.0","State":"Punjab"},{"Net Sales":"7602719.0","Gross Sales":"9141573.0","Total Orders":"1151.0","State":"Tamil Nadu"},{"Net Sales":"7031754.0","Gross Sales":"8374162.0","Total Orders":"917.0","State":"Rajasthan"},{"Net Sales":"6905568.0","Gross Sales":"8043080.0","Total Orders":"851.0","State":"Delhi"},{"Net Sales":"4845410.0","Gross Sales":"5741292.0","Total Orders":"539.0","State":"Assam"},{"Net Sales":"3662425.0","Gross Sales":"4426326.0","Total Orders":"606.0","State":"Orissa"},{"Net Sales":"2825094.0","Gross Sales":"3392051.0","Total Orders":"396.0","State":"Bihar"},{"Net Sales":"2505872.0","Gross Sales":"2997606.0","Total Orders":"301.0","State":"Kerala"},{"Net Sales":"2068040.0","Gross Sales":"2517639.0","Total Orders":"308.0","State":"Jharkhand"},{"Net Sales":"1209160.0","Gross Sales":"1456613.0","Total Orders":"192.0","State":"Chhattisgarh"},{"Net Sales":"774261.0","Gross Sales":"943446.0","Total Orders":"115.0","State":"Jammu and Kashmir"},{"Net Sales":"691257.0","Gross Sales":"823445.0","Total Orders":"115.0","State":"Uttarakhand"}],"chart2":[{"Net Sales":"77673745","Gross Sales":"93089285","Category":"Computer Hardware","Total Orders":"3921.0"},{"Net Sales":"31258020","Gross Sales":"35781255","Category":"Cameras","Total Orders":"2324.0"},{"Net Sales":"22034640","Gross Sales":"27183925","Category":"Mobile Phones","Total Orders":"1708.0"},{"Net Sales":"6729080.0","Gross Sales":"8264008.0","Category":"Footwear","Total Orders":"4869.0"},{"Net Sales":"6109008.0","Gross Sales":"7478195.0","Category":"Clothing","Total Orders":"5242.0"},{"Net Sales":"3913404.0","Gross Sales":"4571000.0","Category":"Watches","Total Orders":"2230.0"}],"chart3":[{"Net Sales":"18236509","Brand":"Lenovo","Gross Sales":"22005850","Total Orders":"536.0"},{"Net Sales":"17023537","Brand":"Samsung","Gross Sales":"20388450","Total Orders":"825.0"},{"Net Sales":"16188967","Brand":"Dell","Gross Sales":"18969500","Total Orders":"470.0"},{"Net Sales":"15204137","Brand":"Apple","Gross Sales":"18300715","Total Orders":"522.0"},{"Net Sales":"12228746","Brand":"Acer","Gross Sales":"14856600","Total Orders":"376.0"},{"Net Sales":"9393591.0","Brand":"Canon","Gross Sales":"10829885","Total Orders":"530.0"},{"Net Sales":"8834931.0","Brand":"Sony","Gross Sales":"10206186","Total Orders":"582.0"},{"Net Sales":"7553995.0","Brand":"HP","Gross Sales":"9140000.0","Total Orders":"650.0"},{"Net Sales":"4648378.0","Brand":"Panasonic","Gross Sales":"5397500.0","Total Orders":"215.0"},{"Net Sales":"3185600.0","Brand":"HTC","Gross Sales":"3939441.0","Total Orders":"222.0"},{"Net Sales":"3140770.0","Brand":"Nikon","Gross Sales":"3503000.0","Total Orders":"162.0"},{"Net Sales":"2212857.0","Brand":"BlackBerry","Gross Sales":"2709592.0","Total Orders":"163.0"},{"Net Sales":"1690579.0","Brand":"Nokia","Gross Sales":"2060283.0","Total Orders":"123.0"},{"Net Sales":"1508540.0","Brand":"Fujifilm","Gross Sales":"1701000.0","Total Orders":"166.0"},{"Net Sales":"1325967.0","Brand":"Adidas","Gross Sales":"1597219.0","Total Orders":"631.0"},{"Net Sales":"1224410.0","Brand":"Aiptek","Gross Sales":"1431500.0","Total Orders":"162.0"},{"Net Sales":"951481.0","Brand":"iBall","Gross Sales":"1187441.0","Total Orders":"175.0"},{"Net Sales":"937719.0","Brand":"Karbon","Gross Sales":"1150374.0","Total Orders":"179.0"},{"Net Sales":"857552.0","Brand":"Sandisk","Gross Sales":"1019420.0","Total Orders":"271.0"},{"Net Sales":"748733.0","Brand":"Epson","Gross Sales":"924500.0","Total Orders":"164.0"},{"Net Sales":"751278.0","Brand":"Clarks","Gross Sales":"923649.0","Total Orders":"591.0"},{"Net Sales":"798741.0","Brand":"Casio","Gross Sales":"922200.0","Total Orders":"326.0"},{"Net Sales":"733871.0","Brand":"Allen Solly","Gross Sales":"903547.0","Total Orders":"527.0"},{"Net Sales":"683561.0","Brand":"Lava","Gross Sales":"841756.0","Total Orders":"109.0"},{"Net Sales":"650119.0","Brand":"Bata","Gross Sales":"800668.0","Total Orders":"425.0"},{"Net Sales":"647665.0","Brand":"Puma","Gross Sales":"795116.0","Total Orders":"516.0"},{"Net Sales":"591223.0","Brand":"Hcl","Gross Sales":"737543.0","Total Orders":"66.0"},{"Net Sales":"618830.0","Brand":"Philips","Gross Sales":"731700.0","Total Orders":"124.0"},{"Net Sales":"604095.0","Brand":"Oxbow","Gross Sales":"696500.0","Total Orders":"166.0"},{"Net Sales":"553783.0","Brand":"Lee cooper","Gross Sales":"676688.0","Total Orders":"273.0"},{"Net Sales":"536804.0","Brand":"Lotto","Gross Sales":"661625.0","Total Orders":"334.0"},{"Net Sales":"539756.0","Brand":"Levi Strauss","Gross Sales":"649513.0","Total Orders":"303.0"},{"Net Sales":"475638.0","Brand":"Transcend","Gross Sales":"589550.0","Total Orders":"106.0"},{"Net Sales":"446589.0","Brand":"Citizen","Gross Sales":"522600.0","Total Orders":"108.0"},{"Net Sales":"447086.0","Brand":"Timex","Gross Sales":"521600.0","Total Orders":"325.0"},{"Net Sales":"359430.0","Brand":"Catwalk","Gross Sales":"445819.0","Total Orders":"398.0"},{"Net Sales":"362310.0","Brand":"Omax","Gross Sales":"431000.0","Total Orders":"216.0"},{"Net Sales":"355095.0","Brand":"Coolpad","Gross Sales":"427500.0","Total Orders":"26.0"},{"Net Sales":"340091.0","Brand":"Byond","Gross Sales":"424818.0","Total Orders":"69.0"},{"Net Sales":"341740.0","Brand":"Adcom","Gross Sales":"423089.0","Total Orders":"70.0"},{"Net Sales":"341961.0","Brand":"Maco","Gross Sales":"418276.0","Total Orders":"289.0"},{"Net Sales":"305361.0","Brand":"Metro","Gross Sales":"377223.0","Total Orders":"263.0"},{"Net Sales":"307683.0","Brand":"Wrangler","Gross Sales":"373149.0","Total Orders":"174.0"},{"Net Sales":"290872.0","Brand":"Van Heusen","Gross Sales":"355362.0","Total Orders":"164.0"},{"Net Sales":"279864.0","Brand":"AND","Gross Sales":"349037.0","Total Orders":"231.0"},{"Net Sales":"289285.0","Brand":"Sonata","Gross Sales":"340000.0","Total Orders":"267.0"},{"Net Sales":"267395.0","Brand":"Compaq","Gross Sales":"332000.0","Total Orders":"50.0"},{"Net Sales":"273760.0","Brand":"Titan","Gross Sales":"324500.0","Total Orders":"167.0"},{"Net Sales":"265115.0","Brand":"Maxima","Gross Sales":"310200.0","Total Orders":"219.0"},{"Net Sales":"212516.0","Brand":"Portia","Gross Sales":"261319.0","Total Orders":"277.0"},{"Net Sales":"203692.0","Brand":"French Connection","Gross Sales":"260306.0","Total Orders":"69.0"},{"Net Sales":"208593.0","Brand":"U S Polo Assn","Gross Sales":"258838.0","Total Orders":"151.0"},{"Net Sales":"199892.0","Brand":"Huawei","Gross Sales":"245100.0","Total Orders":"45.0"},{"Net Sales":"201767.0","Brand":"Killer","Gross Sales":"242237.0","Total Orders":"150.0"},{"Net Sales":"188670.0","Brand":"Lee","Gross Sales":"233026.0","Total Orders":"167.0"},{"Net Sales":"186040.0","Brand":"Red Type","Gross Sales":"230086.0","Total Orders":"104.0"},{"Net Sales":"189460.0","Brand":"Levis","Gross Sales":"230000.0","Total Orders":"55.0"},{"Net Sales":"179850.0","Brand":"Reebok","Gross Sales":"220588.0","Total Orders":"177.0"},{"Net Sales":"186252.0","Brand":"Raymond","Gross Sales":"220427.0","Total Orders":"145.0"},{"Net Sales":"171299.0","Brand":"Arrow","Gross Sales":"205729.0","Total Orders":"137.0"},{"Net Sales":"166391.0","Brand":"Pudu Lifestyle","Gross Sales":"199510.0","Total Orders":"84.0"},{"Net Sales":"159478.0","Brand":"Fastrack","Gross Sales":"183900.0","Total Orders":"112.0"},{"Net Sales":"142873.0","Brand":"Biba","Gross Sales":"177742.0","Total Orders":"164.0"},{"Net Sales":"143207.0","Brand":"Fila","Gross Sales":"176300.0","Total Orders":"194.0"},{"Net Sales":"140812.0","Brand":"Alcalet","Gross Sales":"171087.0","Total Orders":"37.0"},{"Net Sales":"137847.0","Brand":"Nihaar","Gross Sales":"169990.0","Total Orders":"167.0"},{"Net Sales":"136071.0","Brand":"Keona","Gross Sales":"168870.0","Total Orders":"163.0"},{"Net Sales":"141593.0","Brand":"John Players","Gross Sales":"168420.0","Total Orders":"162.0"},{"Net Sales":"138005.0","Brand":"Anahi","Gross Sales":"168341.0","Total Orders":"154.0"},{"Net Sales":"136129.0","Brand":"Mufti","Gross Sales":"162352.0","Total Orders":"82.0"},{"Net Sales":"129510.0","Brand":"TP-Link","Gross Sales":"159100.0","Total Orders":"56.0"},{"Net Sales":"125906.0","Brand":"Cocoon","Gross Sales":"157400.0","Total Orders":"107.0"},{"Net Sales":"128420.0","Brand":"Aneri","Gross Sales":"157386.0","Total Orders":"123.0"},{"Net Sales":"119678.0","Brand":"Derby Jeans Community","Gross Sales":"146086.0","Total Orders":"80.0"},{"Net Sales":"120764.0","Brand":"Lawman","Gross Sales":"141846.0","Total Orders":"83.0"},{"Net Sales":"109309.0","Brand":"Frecultr","Gross Sales":"138411.0","Total Orders":"80.0"},{"Net Sales":"112085.0","Brand":"Adidas Golf","Gross Sales":"135546.0","Total Orders":"55.0"},{"Net Sales":"108303.0","Brand":"Netgear","Gross Sales":"132000.0","Total Orders":"51.0"},{"Net Sales":"103086.0","Brand":"Comfit","Gross Sales":"126241.0","Total Orders":"53.0"},{"Net Sales":"97390.0","Brand":"Microsoft","Gross Sales":"121300.0","Total Orders":"111.0"},{"Net Sales":"99394.0","Brand":"Sparx","Gross Sales":"119033.0","Total Orders":"58.0"},{"Net Sales":"98317.0","Brand":"Levi\u0027s","Gross Sales":"119032.0","Total Orders":"62.0"},{"Net Sales":"94962.0","Brand":"D-Link","Gross Sales":"116500.0","Total Orders":"54.0"},{"Net Sales":"92083.0","Brand":"Sports 52 Wear","Gross Sales":"113407.0","Total Orders":"80.0"},{"Net Sales":"92214.0","Brand":"Moserbaer","Gross Sales":"107975.0","Total Orders":"109.0"},{"Net Sales":"88288.0","Brand":"Woodland","Gross Sales":"107539.0","Total Orders":"54.0"},{"Net Sales":"83586.0","Brand":"Peter England","Gross Sales":"101819.0","Total Orders":"85.0"},{"Net Sales":"80264.0","Brand":"Elle","Gross Sales":"100938.0","Total Orders":"68.0"},{"Net Sales":"80876.0","Brand":"Nivea","Gross Sales":"99438.0","Total Orders":"55.0"},{"Net Sales":"80580.0","Brand":"Wilson","Gross Sales":"97943.0","Total Orders":"53.0"},{"Net Sales":"80931.0","Brand":"Daniel Hechter","Gross Sales":"97077.0","Total Orders":"63.0"},{"Net Sales":"84003.0","Brand":"Q\u0026Q","Gross Sales":"95700.0","Total Orders":"108.0"},{"Net Sales":"75816.0","Brand":"Kraus","Gross Sales":"94383.0","Total Orders":"70.0"},{"Net Sales":"74749.0","Brand":"Indian Terrain","Gross Sales":"90639.0","Total Orders":"79.0"},{"Net Sales":"70741.0","Brand":"Indigo Nation","Gross Sales":"86007.0","Total Orders":"69.0"},{"Net Sales":"66475.0","Brand":"Ayaany","Gross Sales":"81823.0","Total Orders":"70.0"},{"Net Sales":"65225.0","Brand":"Locomotive","Gross Sales":"80567.0","Total Orders":"68.0"},{"Net Sales":"61746.0","Brand":"Kingston","Gross Sales":"73710.0","Total Orders":"108.0"},{"Net Sales":"59346.0","Brand":"Highlander","Gross Sales":"71235.0","Total Orders":"68.0"},{"Net Sales":"55644.0","Brand":"Deal Jeans","Gross Sales":"71110.0","Total Orders":"79.0"},{"Net Sales":"53893.0","Brand":"Gliders","Gross Sales":"66800.0","Total Orders":"58.0"},{"Net Sales":"54411.0","Brand":"Asics","Gross Sales":"66400.0","Total Orders":"53.0"},{"Net Sales":"49312.0","Brand":"Brother","Gross Sales":"61400.0","Total Orders":"54.0"},{"Net Sales":"49113.0","Brand":"Flying Machine","Gross Sales":"61251.0","Total Orders":"80.0"},{"Net Sales":"48929.0","Brand":"Spinn","Gross Sales":"60400.0","Total Orders":"56.0"},{"Net Sales":"52204.0","Brand":"Disney","Gross Sales":"58700.0","Total Orders":"51.0"},{"Net Sales":"47142.0","Brand":"Rocia","Gross Sales":"58400.0","Total Orders":"55.0"},{"Net Sales":"45957.0","Brand":"Kneetoes","Gross Sales":"57300.0","Total Orders":"56.0"},{"Net Sales":"45174.0","Brand":"Go Color","Gross Sales":"54500.0","Total Orders":"51.0"},{"Net Sales":"44206.0","Brand":"Vans","Gross Sales":"53686.0","Total Orders":"54.0"},{"Net Sales":"36504.0","Brand":"Soni","Gross Sales":"45900.0","Total Orders":"56.0"},{"Net Sales":"37041.0","Brand":"Toshiba","Gross Sales":"44700.0","Total Orders":"55.0"},{"Net Sales":"33203.0","Brand":"American Swan","Gross Sales":"41107.0","Total Orders":"82.0"},{"Net Sales":"35883.0","Brand":"Zoop","Gross Sales":"41100.0","Total Orders":"55.0"},{"Net Sales":"29378.0","Brand":"Femella","Gross Sales":"37355.0","Total Orders":"83.0"},{"Net Sales":"26280.0","Brand":"Ninteen","Gross Sales":"33431.0","Total Orders":"80.0"},{"Net Sales":"26241.0","Brand":"Get Wrapped","Gross Sales":"32980.0","Total Orders":"68.0"},{"Net Sales":"25422.0","Brand":"Noi","Gross Sales":"32128.0","Total Orders":"84.0"},{"Net Sales":"24165.0","Brand":"Jealous 26","Gross Sales":"29985.0","Total Orders":"13.0"},{"Net Sales":"23243.0","Brand":"Jealous 25","Gross Sales":"29750.0","Total Orders":"14.0"},{"Net Sales":"22910.0","Brand":"Jealous 24","Gross Sales":"28620.0","Total Orders":"15.0"},{"Net Sales":"16304.0","Brand":"Jealous 23","Gross Sales":"20175.0","Total Orders":"12.0"},{"Net Sales":"12790.0","Brand":"Jealous 21","Gross Sales":"16182.0","Total Orders":"14.0"},{"Net Sales":"12064.0","Brand":"Jealous 22","Gross Sales":"15375.0","Total Orders":"14.0"}],"chart4":[{"Net Sales":"53877081","Gross Sales":"64297749","Total Orders":"7664.0","Order Type":"Contact Center"},{"Net Sales":"50065356","Gross Sales":"59563319","Total Orders":"6729.0","Order Type":"Website"},{"Net Sales":"35409704","Gross Sales":"42471217","Total Orders":"4704.0","Order Type":"Catalogue"},{"Net Sales":"8365756.0","Gross Sales":"10035383","Total Orders":"1197.0","Order Type":"Others"}],"chart5":[{"Net Sales":"28770295","Gross Sales":"34295626","Total Orders":"3981.0","Payment Method":"Debit Card"},{"Net Sales":"28450881","Gross Sales":"34005087","Total Orders":"3886.0","Payment Method":"Credit Card"},{"Net Sales":"25669042","Gross Sales":"30936600","Total Orders":"3482.0","Payment Method":"Cash on Delivery"},{"Net Sales":"23722715","Gross Sales":"28286036","Total Orders":"3388.0","Payment Method":"Gift Coupons"},{"Net Sales":"21319344","Gross Sales":"25278569","Total Orders":"2890.0","Payment Method":"Net Banking"},{"Net Sales":"19785620","Gross Sales":"23565750","Total Orders":"2667.0","Payment Method":"Credit Card EMI"}]}